yprinciple/__init__.py
yprinciple/genapi.py
yprinciple/gengrid.py
yprinciple/profiler.py
yprinciple/smw_targets.py
yprinciple/target.py
yprinciple/version.py
yprinciple/ypcell.py
yprinciple/ypgen.py
yprinciple/ypgenapp.py
py_yprinciple_gen-0.4.2.dist-info/METADATA
py_yprinciple_gen-0.4.2.dist-info/WHEEL
py_yprinciple_gen-0.4.2.dist-info/entry_points.txt
py_yprinciple_gen-0.4.2.dist-info/licenses/LICENSE
py_yprinciple_gen-0.4.2.dist-info/RECORD
