Metadata-Version: 2.4
Name: py-yprinciple-gen
Version: 0.4.2
Dynamic: Summary
Project-URL: Home, https://github.com/WolfgangFahl/py-yprinciple-gen
Project-URL: Documentation, https://wiki.bitplan.com/index.php/Py-yprinciple-gen
Project-URL: Source, https://github.com/WolfgangFahl/py-yprinciple-gen
Author-email: Wolfgang Fahl <wf@bitplan.com>
Maintainer-email: Wolfgang Fahl <wf@bitplan.com>
License-Expression: Apache-2.0
License-File: LICENSE
Classifier: Development Status :: 4 - Beta
Classifier: Environment :: Web Environment
Classifier: Intended Audience :: Developers
Classifier: Intended Audience :: Education
Classifier: Intended Audience :: Science/Research
Classifier: License :: OSI Approved :: Apache Software License
Classifier: Operating System :: OS Independent
Classifier: Programming Language :: Python :: 3 :: Only
Classifier: Programming Language :: Python :: 3.10
Classifier: Programming Language :: Python :: 3.11
Classifier: Programming Language :: Python :: 3.12
Classifier: Programming Language :: Python :: 3.13
Classifier: Topic :: Software Development
Requires-Python: >=3.10
Requires-Dist: beautifulsoup4
Requires-Dist: ngwidgets>=0.29.4
Requires-Dist: py-3rdparty-mediawiki>=0.17.0
Requires-Dist: pymetamodel>=0.6.5
Requires-Dist: search-engine-parser>=0.6.8
Provides-Extra: test
Requires-Dist: green; extra == 'test'
